plover_vcs/__init__.py
plover_vcs/__main__.py
plover_vcs/file_watcher.py
plover_vcs/plover_vcs.py
plover_vcs/resources_rc.py
plover_vcs/vcs_config.py
plover_vcs/message_generator/__init__.py
plover_vcs/message_generator/git_diff_message_generator.py
plover_vcs/message_generator/line_changes.py
plover_vcs/message_generator/message_generator.py
plover_vcs/ui/__init__.py
plover_vcs/ui/vcs_settings.py
plover_vcs/ui/vcs_settings_ui.py
plover_vcs/vcs/__init__.py
plover_vcs/vcs/exception_decorator.py
plover_vcs/vcs/git_vcs_service.py
plover_vcs/vcs/vcs_exception.py
plover_vcs/vcs/vcs_service.py
plover_vcs/vcs/vcs_service_factory.py
plover_vcs_plugin-0.1.6.dist-info/LICENSE
plover_vcs_plugin-0.1.6.dist-info/METADATA
plover_vcs_plugin-0.1.6.dist-info/WHEEL
plover_vcs_plugin-0.1.6.dist-info/entry_points.txt
plover_vcs_plugin-0.1.6.dist-info/top_level.txt
plover_vcs_plugin-0.1.6.dist-info/zip-safe
plover_vcs_plugin-0.1.6.dist-info/RECORD
