Metadata-Version: 2.1
Name: plover-vcs-plugin
Version: 0.1.6
Summary: Automated version control for Plover
Home-page: https://github.com/levimdmiller/plover-vcs-plugin
Author: Levi Miller
Author-email: levi@levimiller.ca
License: GNU General Public License v3 (GPLv3)
Keywords: plover plover_plugin
Platform: UNKNOWN
Classifier: Development Status :: 1 - Planning
Classifier: Environment :: Plugins
Classifier: Intended Audience :: End Users/Desktop
Classifier: License :: OSI Approved :: GNU General Public License v3 (GPLv3)
Classifier: Operating System :: OS Independent
Classifier: Programming Language :: Python :: 3
Classifier: Programming Language :: Python :: 3.5
Requires-Dist: plover (>=4.0.0.dev7)
Requires-Dist: gitpython (>=2.1.12)
